octo_onedrive/__init__.py
octo_onedrive/_version.py
octo_onedrive/onedrive.py
octo_onedrive-0.0.10.dist-info/LICENSE.md
octo_onedrive-0.0.10.dist-info/METADATA
octo_onedrive-0.0.10.dist-info/WHEEL
octo_onedrive-0.0.10.dist-info/top_level.txt
octo_onedrive-0.0.10.dist-info/RECORD
