Metadata-Version: 2.1
Name: octo-onedrive
Version: 0.0.10
Summary: OctoPrint OneDrive Communication Module
Home-page: https://github.com/cp2004/Octo-OneDrive
Author: Charlie Powell
Author-email: cp2004.github@gmail.com
Project-URL: Bug Tracker, https://github.com/cp2004/Octo-OneDrive/issues
Classifier: Programming Language :: Python :: 3 :: Only
Classifier: License :: OSI Approved :: GNU Affero General Public License v3
Classifier: Operating System :: OS Independent
Classifier: Development Status :: 5 - Production/Stable
Requires-Python: >=3.7
License-File: LICENSE.md
Requires-Dist: msal <2,>=1.26.0
Requires-Dist: cryptography <43,>=42.0.4
Requires-Dist: python-dateutil
Provides-Extra: develop
Requires-Dist: pre-commit ; extra == 'develop'
